cool_config/__init__.py
cool_config/config_parser.py
cool_config/cool_config.py
cool_config/example.py
cool_config/exceptions.py
cool_config/utils.py
cool_config-0.2.3.dist-info/METADATA
cool_config-0.2.3.dist-info/WHEEL
cool_config-0.2.3.dist-info/top_level.txt
cool_config-0.2.3.dist-info/RECORD
