Metadata-Version: 2.1
Name: cool-config
Version: 0.2.3
Summary: Another Python configuration tool
Home-page: https://github.com/strangecamelcaselogin/cool_config
Author: strangecamelcaselogin
Author-email: strangecamelcaselogin@gmail.com
License: MIT
Platform: UNKNOWN
Classifier: Development Status :: 3 - Alpha
Classifier: License :: OSI Approved :: MIT License
Classifier: Programming Language :: Python :: 3.6
Requires-Python: >=3.6
Requires-Dist: pyyaml (>=4.2b1)
